{
    "keywords": [
        {
            "keyword_merged": "office 365",
            "sum_traffic": 52246,
            "volume_merged": 3690000,
            "sum_traffic_prev": 81635,
            "best_position": 13,
            "best_position_prev": 11,
            "sum_traffic_merged": 52246,
            "best_position_url": "https://www.godaddy.com/business/office-365"
        },
        {
            "keyword_merged": "domain name search",
            "sum_traffic": 22143,
            "volume_merged": 34000,
            "sum_traffic_prev": 8414,
            "best_position": 1,
            "best_position_prev": 2,
            "sum_traffic_merged": 22143,
            "best_position_url": "https://www.godaddy.com/domains"
        },
        {
            "keyword_merged": "whois lookup",
            "sum_traffic": 13056,
            "volume_merged": 149000,
            "sum_traffic_prev": 4308,
            "best_position": 3,
            "best_position_prev": 4,
            "sum_traffic_merged": 13056,
            "best_position_url": "https://www.godaddy.com/whois"
        },
        {
            "keyword_merged": "domain names",
            "sum_traffic": 7709,
            "volume_merged": 34000,
            "sum_traffic_prev": 15419,
            "best_position": 2,
            "best_position_prev": 1,
            "sum_traffic_merged": 7709,
            "best_position_url": "https://www.godaddy.com/domains"
        },
        {
            "keyword_merged": "buy domain",
            "sum_traffic": 4288,
            "volume_merged": 19000,
            "sum_traffic_prev": 1912,
            "best_position": 1,
            "best_position_prev": 3,
            "sum_traffic_merged": 4288,
            "best_position_url": "https://www.godaddy.com/domains"
        },
        {
            "keyword_merged": "domain name",
            "sum_traffic": 3450,
            "volume_merged": 33000,
            "sum_traffic_prev": 1171,
            "best_position": 3,
            "best_position_prev": 4,
            "sum_traffic_merged": 3450,
            "best_position_url": "https://www.godaddy.com/domains"
        },
        {
            "keyword_merged": "domain lookup",
            "sum_traffic": 2929,
            "volume_merged": 23000,
            "sum_traffic_prev": 4204,
            "best_position": 4,
            "best_position_prev": 3,
            "sum_traffic_merged": 2929,
            "best_position_url": "https://www.godaddy.com/whois"
        },
        {
            "keyword_merged": "365",
            "sum_traffic": 2702,
            "volume_merged": 307000,
            "sum_traffic_prev": 1107,
            "best_position": 15,
            "best_position_prev": 19,
            "sum_traffic_merged": 2702,
            "best_position_url": "https://www.godaddy.com/business/office-365"
        },
        {
            "keyword_merged": "domain check",
            "sum_traffic": 2646,
            "volume_merged": 8700,
            "sum_traffic_prev": 1900,
            "best_position": 1,
            "best_position_prev": 2,
            "sum_traffic_merged": 2646,
            "best_position_url": "https://www.godaddy.com/domains"
        },
        {
            "keyword_merged": "domain name generator",
            "sum_traffic": 2363,
            "volume_merged": 6800,
            "sum_traffic_prev": 827,
            "best_position": 2,
            "best_position_prev": 3,
            "sum_traffic_merged": 2363,
            "best_position_url": "https://www.godaddy.com/domains/domain-name-generator"
        }
    ]
}